nato_phonetic/__init__.py
nato_phonetic/__main__.py
nato_phonetic/cli.py
nato_phonetic/core.py
nato_phonetic/entrypoint.py
phonetic_nato-0.2.0.dist-info/METADATA
phonetic_nato-0.2.0.dist-info/WHEEL
phonetic_nato-0.2.0.dist-info/entry_points.txt
phonetic_nato-0.2.0.dist-info/licenses/LICENSE
phonetic_nato-0.2.0.dist-info/RECORD
