Metadata-Version: 2.4
Name: phonetic-nato
Version: 0.2.0
Summary: A beautiful CLI for the NATO phonetic alphabet built with Python, Click, and Rich
Project-URL: Homepage, https://trtmn.io/nato-phonetic-alphabet
Project-URL: Repository, https://codeberg.org/trtmn/nato-phonetic-alphabet
Project-URL: Issues, https://codeberg.org/trtmn/nato-phonetic-alphabet/issues
Author-email: "Matt (Fishy) Troutman" <git@trtmn.com>
License: Creative Commons Attribution-ShareAlike 4.0 International
License-File: LICENSE
Classifier: Development Status :: 3 - Alpha
Classifier: Intended Audience :: End Users/Desktop
Classifier: Programming Language :: Python :: 3
Classifier: Programming Language :: Python :: 3.11
Classifier: Programming Language :: Python :: 3.12
Classifier: Topic :: Communications
Classifier: Topic :: Utilities
Requires-Python: >=3.11
Requires-Dist: click>=8.0.0
Requires-Dist: rich>=13.0.0
Provides-Extra: dev
Requires-Dist: black>=23.0.0; extra == 'dev'
Requires-Dist: flake8>=6.0.0; extra == 'dev'
Requires-Dist: mypy>=1.0.0; extra == 'dev'
Requires-Dist: pytest-cov>=4.0.0; extra == 'dev'
Requires-Dist: pytest>=7.0.0; extra == 'dev'
